bandpage
