Metadata-Version: 1.1
Name: bandpage
Version: 1.0.1
Summary: The Python library for BandPage
Home-page: https://github.com/mattrobenolt/python-bandpage
Author: Matt Robenolt
Author-email: matt@ydekproductions.com
License: BSD
Platform: UNKNOWN
Classifier: Development Status :: 4 - Beta
Classifier: Intended Audience :: Developers
Classifier: License :: OSI Approved :: GNU General Public License (GPL)
Classifier: Operating System :: OS Independent
Classifier: Topic :: Software Development
